MANIFEST.in
setup.py
chosenadmin/__init__.py
chosenadmin/middleware.py
chosenadmin/__pycache__/__init__.cpython-34.pyc
chosenadmin/__pycache__/__init__.cpython-36.pyc
chosenadmin/__pycache__/middleware.cpython-34.pyc
chosenadmin/__pycache__/middleware.cpython-36.pyc
chosenadmin/static/.DS_Store
django_chosenadmin.egg-info/PKG-INFO
django_chosenadmin.egg-info/SOURCES.txt
django_chosenadmin.egg-info/dependency_links.txt
django_chosenadmin.egg-info/top_level.txt