Metadata-Version: 1.1
Name: django-chosenadmin
Version: 0.4.0
Summary: Adds Chosen.js to the Django Admin app
Home-page: https://github.com/bradmontgomery/django-chosenadmin/archive/v0.4.0.tar.gz
Author: Brad Montgomery
Author-email: brad@bradmontgomery.net
License: MIT
Keywords: django chosen admin
Platform: UNKNOWN
Classifier: Development Status :: 4 - Beta
Classifier: Environment :: Web Environment
Classifier: Intended Audience :: Developers
Classifier: License :: OSI Approved :: MIT License
Classifier: Operating System :: OS Independent
Classifier: Programming Language :: Python
Classifier: Programming Language :: Python :: 3
Classifier: Programming Language :: Python :: 3.4
Classifier: Programming Language :: Python :: 3.5
Classifier: Programming Language :: Python :: 3.6
Classifier: Topic :: Internet :: WWW/HTTP
Classifier: Framework :: Django
Classifier: Topic :: Utilities
